mechanics.py
mechanics-0.1.3.dist-info/METADATA
mechanics-0.1.3.dist-info/WHEEL
mechanics-0.1.3.dist-info/top_level.txt
mechanics-0.1.3.dist-info/RECORD
