Metadata-Version: 2.1
Name: mechanics
Version: 0.1.3
Summary: A library for solving simple mechanics problems
Home-page: UNKNOWN
Author: alextras
Author-email: alextrasias@gmail.com
License: UNKNOWN
Platform: UNKNOWN
